<?xml version="1.0" encoding="utf-8"?>
<beans xmlns="http://www.springframework.org/schema/beans" xmlns:xsi="http://www.w3.org/2001/XMLSchema-instance"
    xmlns:mvc="http://www.springframework.org/schema/mvc" xmlns:context="http://www.springframework.org/schema/context"
    xmlns:websocket="http://www.springframework.org/schema/websocket" xmlns:util="http://www.springframework.org/schema/util"
    xsi:schemaLocation="
        http://www.springframework.org/schema/mvc http://www.springframework.org/schema/mvc/spring-mvc.xsd
        http://www.springframework.org/schema/beans http://www.springframework.org/schema/beans/spring-beans.xsd
        http://www.springframework.org/schema/websocket http://www.springframework.org/schema/websocket/spring-websocket.xsd
        http://www.springframework.org/schema/context http://www.springframework.org/schema/context/spring-context.xsd
        http://www.springframework.org/schema/util http://www.springframework.org/schema/util/spring-util.xsd">

    <!-- 系统监控 -->
    <context:component-scan base-package="net.breakidea.common.config" />

    <!-- 默认配置 -->
    <context:property-placeholder location="classpath:default.properties" order="1024" />

    <!-- 模板配置 -->
    <bean class="org.springframework.web.servlet.view.velocity.VelocityConfigurer">
        <property name="configLocation" value="/WEB-INF/velocity.properties" />
        <property name="resourceLoaderPath">
            <value>/WEB-INF/views,classpath:internal,/WEB-INF/external,file://${view.external.path}</value>
        </property>
        <property name="velocityProperties">
            <props>
                <prop key="input.encoding">utf-8</prop>
                <prop key="output.encoding">utf-8</prop>
                <prop key="velocimacro.library">library.vm,macro.vm</prop>
                <prop key="eventhandler.referenceinsertion.class">net.breakidea.common.support.view.EscapeHtmlReference</prop>
            </props>
        </property>
    </bean>

    <!-- 视图配置 -->
    <bean class="org.springframework.web.servlet.view.ViewResolverComposite">
        <property name="order" value="0" />
        <property name="viewResolvers">
            <list>
                <bean class="org.springframework.web.servlet.view.BeanNameViewResolver" />
                <bean class="org.springframework.web.servlet.view.velocity.VelocityViewResolver">
                    <property name="viewClass" value="net.breakidea.common.support.view.BetterVelocityView" />
                    <property name="suffix" value=".vm" />
                    <property name="toolboxConfigLocation" value="/WEB-INF/toolbox.xml" />
                </bean>
            </list>
        </property>
    </bean>

    <!-- 拦截器 -->
    <mvc:interceptors>
        <bean class="net.breakidea.common.support.ProcessingInterceptor" />
    </mvc:interceptors>

    <!-- 异常处理 -->
    <bean class="net.breakidea.common.support.SimpleExceptionResolver" />

</beans>